apigpio/__init__.py
apigpio/apigpio.py
apigpio/ctes.py
apigpio/utils.py
apigpio-0.0.2.dist-info/DESCRIPTION.rst
apigpio-0.0.2.dist-info/METADATA
apigpio-0.0.2.dist-info/RECORD
apigpio-0.0.2.dist-info/WHEEL
apigpio-0.0.2.dist-info/metadata.json
apigpio-0.0.2.dist-info/top_level.txt
