Metadata-Version: 2.0
Name: apigpio
Version: 0.0.2
Summary: asyncio-based python client for pigpiod
Home-page: https://github.com/PierreRust/apigpio
Author: Pierre Rust
Author-email: pierre.rust@gmail.com
License: UNKNOWN
Download-URL: https://github.com/PierreRust/apigpio/archive/0.0.2.tar.gz
Keywords: gpio,pigpio,asyncio,raspberry
Platform: UNKNOWN
Classifier: Development Status :: 3 - Alpha
Classifier: Intended Audience :: Developers
Classifier: License :: OSI Approved :: MIT License
Classifier: Operating System :: OS Independent
Classifier: Programming Language :: Python :: 3.4
Classifier: Topic :: System :: Hardware :: Hardware Drivers
Classifier: Topic :: Software Development :: Libraries :: Python Modules
